citention/__init__.py
citention/citation_scorers/base_citation_scorer.py
citention/citation_scorers/citation_scorers.py
citention/citation_scorers/util.py
citention/model/attention_attributor.py
citention/model/citention_model.py
citention/model/score_combinator.py
citention/model/score_estimator.py
citention/model/task.py
citention/retrievers/base_retriever.py
citention/retrievers/bm25_retriever.py
citention/retrievers/sbert_retriever.py
citention/retrievers/util.py
citention/trainers/bm25_trainer.py
citention/trainers/qr_head_trainer.py
citention/trainers/score_combinator_trainer.py
citention/trainers/util.py
citention/util/misc.py
citention/util/response_processor.py
citention-0.0.1.dist-info/licenses/LICENSE
citention-0.0.1.dist-info/METADATA
citention-0.0.1.dist-info/WHEEL
citention-0.0.1.dist-info/top_level.txt
citention-0.0.1.dist-info/RECORD
