Metadata-Version: 2.4
Name: citention
Version: 0.0.1
Summary: A tool for citation using transformer models.
License-Expression: Apache-2.0
Project-URL: Homepage, https://github.com/UKPLab/citention
Requires-Python: >=3.10
License-File: LICENSE
Requires-Dist: at2
Requires-Dist: transformers
Requires-Dist: torch
Requires-Dist: numpy
Requires-Dist: scikit-learn
Requires-Dist: tqdm
Requires-Dist: rank-bm25
Requires-Dist: sentence-transformers
Provides-Extra: dev
Requires-Dist: pytest; extra == "dev"
Dynamic: license-file
